MANIFEST.in
README.rst
setup.cfg
setup.py
calendarevents/__init__.py
calendarevents/bootstrap.py
calendarevents/helpers.py
calendarevents/partials.py
calendarevents/controllers/__init__.py
calendarevents/controllers/calendar.py
calendarevents/controllers/event.py
calendarevents/controllers/root.py
calendarevents/lib/__init__.py
calendarevents/lib/event_type.py
calendarevents/lib/forms.py
calendarevents/lib/utils.py
calendarevents/lib/validators.py
calendarevents/lib/weather.py
calendarevents/model/__init__.py
calendarevents/model/models.py
calendarevents/public/__init__.py
calendarevents/public/css/fullcalendar.css
calendarevents/public/css/style.css
calendarevents/public/images/calendar.png
calendarevents/public/images/mod.gif
calendarevents/public/images/noweather.png
calendarevents/public/images/trash.gif
calendarevents/public/js/calendarevents.js
calendarevents/public/js/fullcalendar.min.js
calendarevents/public/js/jquery.min.js
calendarevents/public/js/moment.min.js
calendarevents/templates/__init__.py
calendarevents/templates/calendar/__init__.py
calendarevents/templates/calendar/calendar.html
calendarevents/templates/calendar/events.html
calendarevents/templates/calendar/list.html
calendarevents/templates/calendar/new.html
calendarevents/templates/event/__init__.py
calendarevents/templates/event/edit.html
calendarevents/templates/event/event.html
calendarevents/templates/event/new.html
calendarevents/templates/partials/__init__.py
calendarevents/templates/partials/calendar.html
calendarevents/templates/partials/event.html
tests/__init__.py
tests/base.py
tests/test_controller.py
tests/test_utils.py
tests/controllers/__init__.py
tests/controllers/root.py
tests/templates/__init__.py
tgapp_calendarevents.egg-info/PKG-INFO
tgapp_calendarevents.egg-info/SOURCES.txt
tgapp_calendarevents.egg-info/dependency_links.txt
tgapp_calendarevents.egg-info/entry_points.txt
tgapp_calendarevents.egg-info/not-zip-safe
tgapp_calendarevents.egg-info/requires.txt
tgapp_calendarevents.egg-info/top_level.txt