Metadata-Version: 2.1
Name: tgapp-calendarevents
Version: 0.2.1
Summary: TurboGears2 pluggable application for events and calendars
Home-page: UNKNOWN
Author: Alessandro Molina
Author-email: alessandro.molina@axant.it
License: UNKNOWN
Keywords: turbogears2.application
Platform: UNKNOWN
Provides-Extra: testing
